<?xml version="1.0" encoding="UTF-8"?><record_update sys_domain="global" table="sys_app_module">
    <sys_app_module action="DELETE">
        <active>true</active>
        <application/>
        <assessment/>
        <device_type/>
        <filter/>
        <hint/>
        <homepage/>
        <image/>
        <link_type>LIST</link_type>
        <map_page/>
        <mobile_title>Demo Table 2s</mobile_title>
        <mobile_view_name>Mobile</mobile_view_name>
        <name>x_1129234_starb_m_demo_table_2</name>
        <order/>
        <override_menu_roles>false</override_menu_roles>
        <query/>
        <report/>
        <roles>x_1129234_starb_m.demo_table_2_user</roles>
        <sys_class_name>sys_app_module</sys_class_name>
        <sys_created_by>admin</sys_created_by>
        <sys_created_on>2023-11-21 08:13:44</sys_created_on>
        <sys_domain>global</sys_domain>
        <sys_domain_path>/</sys_domain_path>
        <sys_id>d1644ec79726b5506823f5c11153afce</sys_id>
        <sys_mod_count>0</sys_mod_count>
        <sys_name>Demo Table 2s</sys_name>
        <sys_overrides/>
        <sys_package display_value="Starbucks Management" source="x_1129234_starb_m">73aa7265975a71106823f5c11153afe4</sys_package>
        <sys_policy/>
        <sys_scope display_value="Starbucks Management">73aa7265975a71106823f5c11153afe4</sys_scope>
        <sys_update_name>sys_app_module_d1644ec79726b5506823f5c11153afce</sys_update_name>
        <sys_updated_by>admin</sys_updated_by>
        <sys_updated_on>2023-11-21 08:13:44</sys_updated_on>
        <timeline_page/>
        <title>Demo Table 2s</title>
        <uncancelable>false</uncancelable>
        <view_name/>
        <window_name/>
    </sys_app_module>
    <sys_update_version action="INSERT_OR_UPDATE">
        <action>DELETE</action>
        <application display_value="Starbucks Management">73aa7265975a71106823f5c11153afe4</application>
        <file_path/>
        <instance_id>c2d9444fdbc54d107527d7c8f49619cc</instance_id>
        <instance_name>dev121859</instance_name>
        <name>sys_app_module_d1644ec79726b5506823f5c11153afce</name>
        <payload><![CDATA[<?xml version="1.0" encoding="UTF-8"?><record_update sys_domain="global" table="sys_app_module"><sys_app_module action="INSERT_OR_UPDATE"><active>true</active><application/><assessment/><device_type/><filter/><hint/><homepage/><image/><link_type>LIST</link_type><map_page/><mobile_title>Demo Table 2s</mobile_title><mobile_view_name>Mobile</mobile_view_name><name>x_1129234_starb_m_demo_table_2</name><order/><override_menu_roles>false</override_menu_roles><query/><report/><roles>x_1129234_starb_m.demo_table_2_user</roles><sys_class_name>sys_app_module</sys_class_name><sys_created_by>admin</sys_created_by><sys_created_on>2023-11-21 08:13:44</sys_created_on><sys_domain>global</sys_domain><sys_domain_path>/</sys_domain_path><sys_id>d1644ec79726b5506823f5c11153afce</sys_id><sys_mod_count>0</sys_mod_count><sys_name>Demo Table 2s</sys_name><sys_overrides/><sys_package display_value="Starbucks Management" source="x_1129234_starb_m">73aa7265975a71106823f5c11153afe4</sys_package><sys_policy/><sys_scope display_value="Starbucks Management">73aa7265975a71106823f5c11153afe4</sys_scope><sys_update_name>sys_app_module_d1644ec79726b5506823f5c11153afce</sys_update_name><sys_updated_by>admin</sys_updated_by><sys_updated_on>2023-11-21 08:13:44</sys_updated_on><timeline_page/><title>Demo Table 2s</title><uncancelable>false</uncancelable><view_name/><window_name/></sys_app_module></record_update>]]></payload>
        <payload_hash>380398418</payload_hash>
        <record_name>Demo Table 2s</record_name>
        <reverted_from/>
        <source>b47b4b65979a71106823f5c11153af26</source>
        <source_table>sys_update_set</source_table>
        <state>previous</state>
        <sys_created_by>admin</sys_created_by>
        <sys_created_on>2023-11-22 05:22:21</sys_created_on>
        <sys_id>f8c6ee9397a6f5506823f5c11153aff0</sys_id>
        <sys_mod_count>0</sys_mod_count>
        <sys_recorded_at>18bf57ab6720000001</sys_recorded_at>
        <sys_updated_by>admin</sys_updated_by>
        <sys_updated_on>2023-11-22 05:22:21</sys_updated_on>
        <type>Module</type>
        <update_guid>d164460b3626b55069505c4a88d0bb64</update_guid>
        <update_guid_history>d164460b3626b55069505c4a88d0bb64:-1565621696,d164460b3626b55069505c4a88d0bb64:-1565621696</update_guid_history>
    </sys_update_version>
    <sys_metadata_delete action="INSERT_OR_UPDATE">
        <sys_audit_delete display_value="Demo Table 2s">27c662d397a6f5506823f5c11153af0c</sys_audit_delete>
        <sys_class_name>sys_metadata_delete</sys_class_name>
        <sys_created_by>admin</sys_created_by>
        <sys_created_on>2023-11-22 05:22:32</sys_created_on>
        <sys_db_object display_value="" name="sys_app_module">sys_app_module</sys_db_object>
        <sys_id>2267bff68f5342b38f1d6202b431bf99</sys_id>
        <sys_metadata>d1644ec79726b5506823f5c11153afce</sys_metadata>
        <sys_mod_count>0</sys_mod_count>
        <sys_name>Demo Table 2s</sys_name>
        <sys_package display_value="Starbucks Management" source="x_1129234_starb_m">73aa7265975a71106823f5c11153afe4</sys_package>
        <sys_parent/>
        <sys_policy/>
        <sys_scope display_value="Starbucks Management">73aa7265975a71106823f5c11153afe4</sys_scope>
        <sys_scope_delete display_value="">59445402b425491480e3057de7443a84</sys_scope_delete>
        <sys_update_name>sys_app_module_d1644ec79726b5506823f5c11153afce</sys_update_name>
        <sys_update_version display_value="sys_app_module_d1644ec79726b5506823f5c11153afce">f8c6ee9397a6f5506823f5c11153aff0</sys_update_version>
        <sys_updated_by>admin</sys_updated_by>
        <sys_updated_on>2023-11-22 05:22:32</sys_updated_on>
    </sys_metadata_delete>
</record_update>
